{"chunk_definitions":[{"row":18,"row_count":1,"visible":true,"expansion_state":0,"options":{"engine":"r","label":"unnamed-chunk-50","dev":"png"},"document_id":"5F889288","chunk_id":"cqw2bvbbnu6zv","chunk_label":"unnamed-chunk-2"},{"row":378,"row_count":1,"visible":true,"expansion_state":0,"options":{"engine":"r","label":"unnamed-chunk-51","dev":"png"},"document_id":"5F889288","chunk_id":"cq35lw17ciy8k","chunk_label":"unnamed-chunk-31"},{"row":392,"row_count":1,"visible":true,"expansion_state":0,"options":{"engine":"r","label":"unnamed-chunk-52","dev":"png"},"document_id":"5F889288","chunk_id":"cnzm4irz0720n","chunk_label":"unnamed-chunk-33"},{"row":429,"row_count":1,"visible":true,"expansion_state":0,"options":{"engine":"r","label":"unnamed-chunk-53","dev":"png"},"document_id":"5F889288","chunk_id":"cb7dk4e5jbucq","chunk_label":"unnamed-chunk-37"},{"row":453,"row_count":1,"visible":true,"expansion_state":0,"options":{"engine":"r","label":"unnamed-chunk-54","dev":"png"},"document_id":"5F889288","chunk_id":"c5tmqmkq3ylxq","chunk_label":"unnamed-chunk-39"},{"row":490,"row_count":1,"visible":true,"expansion_state":0,"options":{"engine":"r","label":"unnamed-chunk-55","dev":"png"},"document_id":"5F889288","chunk_id":"cid8y53c1dj6j","chunk_label":"unnamed-chunk-43"}],"doc_write_time":1712318472,"chunk_rendered_width":476}